{"npi":"1003985755","name":"COUNTY OF SAN MATEO","state":"CA","city":"SAN MATEO","classification":"General Acute Care Hospital","total_paid":75655410.78000003,"total_claims":3295107.0,"distinct_procedures":574,"avg_per_claim":22.96,"avg_per_claim_zscore":-0.39,"classification_avg_per_claim":68.61,"yearly":[{"year":"2018","total_paid":10756047.72,"total_claims":475399.0,"active_providers":0,"total_beneficiaries":401585.0},{"year":"2019","total_paid":10228040.570000006,"total_claims":460972.0,"active_providers":0,"total_beneficiaries":397994.0},{"year":"2020","total_paid":6366165.880000002,"total_claims":301762.0,"active_providers":0,"total_beneficiaries":271547.0},{"year":"2021","total_paid":8721610.730000004,"total_claims":404525.0,"active_providers":0,"total_beneficiaries":372059.0},{"year":"2022","total_paid":11300909.629999997,"total_claims":489091.0,"active_providers":0,"total_beneficiaries":447270.0},{"year":"2023","total_paid":13354734.810000006,"total_claims":566824.0,"active_providers":0,"total_beneficiaries":518689.0},{"year":"2024","total_paid":14927901.439999998,"total_claims":596534.0,"active_providers":0,"total_beneficiaries":547173.0}],"monthly":null,"top_procedures":[{"code":"0510","description":"","total_paid":12574628.979999999,"total_claims":431823.0},{"code":"0450","description":"","total_paid":5587781.109999999,"total_claims":92514.0},{"code":"G0463","description":"Hospital outpt clinic visit","total_paid":3725225.5,"total_claims":96405.0},{"code":"87636","description":"Sarscov2 & inf a&b amp prb","total_paid":3559084.11,"total_claims":24679.0},{"code":"Z7502","description":"","total_paid":2048836.8299999994,"total_claims":55257.0},{"code":"J7307","description":"Etonogestrel implant system","total_paid":1492686.44,"total_claims":1204.0},{"code":"77067","description":"Scr mammo bi incl cad","total_paid":1461894.59,"total_claims":17547.0},{"code":"80307","description":"Drug test prsmv chem anlyzr","total_paid":1321459.0800000003,"total_claims":11210.0},{"code":"80053","description":"Comprehen metabolic panel","total_paid":1294995.16,"total_claims":144572.0},{"code":"86480","description":"Tb test cell immun measure","total_paid":1139184.29,"total_claims":24401.0}],"medicare":null}