{"npi":"1154366649","name":"SUPPORT INCORPORATED","state":"NC","city":"GASTONIA","classification":"Foster Care Agency","total_paid":37787924.10999998,"total_claims":151811.0,"distinct_procedures":8,"avg_per_claim":248.91,"avg_per_claim_zscore":-0.16,"classification_avg_per_claim":350.99,"yearly":[{"year":"2018","total_paid":4334820.15,"total_claims":20056.0,"active_providers":0,"total_beneficiaries":1448.0},{"year":"2019","total_paid":5181802.71,"total_claims":22083.0,"active_providers":0,"total_beneficiaries":1872.0},{"year":"2020","total_paid":5811500.750000001,"total_claims":24404.0,"active_providers":0,"total_beneficiaries":2265.0},{"year":"2021","total_paid":5542820.9399999995,"total_claims":22275.0,"active_providers":0,"total_beneficiaries":2374.0},{"year":"2022","total_paid":4970065.750000001,"total_claims":19045.0,"active_providers":0,"total_beneficiaries":2166.0},{"year":"2023","total_paid":5863593.81,"total_claims":23014.0,"active_providers":0,"total_beneficiaries":2887.0},{"year":"2024","total_paid":6083320.0,"total_claims":20934.0,"active_providers":0,"total_beneficiaries":3142.0}],"monthly":null,"top_procedures":[{"code":"H2022","description":"Com wrap-around sv, per diem","total_paid":18639794.84,"total_claims":68027.0},{"code":"S5145","description":"Child fostercare th per diem","total_paid":14043938.84,"total_claims":74394.0},{"code":"H0032","description":"Mh svc plan dev by non-md","total_paid":4117996.29,"total_claims":4581.0},{"code":"T1017","description":"Targeted case management","total_paid":775839.43,"total_claims":2825.0},{"code":"90837","description":"Psytx w pt 60 minutes","total_paid":157526.95,"total_claims":1642.0},{"code":"H2022CR","description":"","total_paid":23100.06,"total_claims":96.0},{"code":"H2022GT","description":"","total_paid":19431.0,"total_claims":81.0},{"code":"90834","description":"Psytx w pt 45 minutes","total_paid":10296.699999999999,"total_claims":165.0}],"medicare":null}