{"npi":"1376577247","name":"ALBANY MEDICAL CENTER HOSPITAL","state":"NY","city":"ALBANY","classification":"General Acute Care Hospital","total_paid":79775113.89999995,"total_claims":1299838.0,"distinct_procedures":500,"avg_per_claim":61.37,"avg_per_claim_zscore":-0.06,"classification_avg_per_claim":68.61,"yearly":[{"year":"2018","total_paid":668823.5,"total_claims":13971.0,"active_providers":0,"total_beneficiaries":12648.0},{"year":"2019","total_paid":4712360.469999999,"total_claims":86448.0,"active_providers":0,"total_beneficiaries":77898.0},{"year":"2020","total_paid":14755954.740000004,"total_claims":219754.0,"active_providers":0,"total_beneficiaries":196389.0},{"year":"2021","total_paid":15152679.900000002,"total_claims":246291.0,"active_providers":0,"total_beneficiaries":221015.0},{"year":"2022","total_paid":15049165.21,"total_claims":249802.0,"active_providers":0,"total_beneficiaries":225864.0},{"year":"2023","total_paid":16843131.289999995,"total_claims":265983.0,"active_providers":0,"total_beneficiaries":240150.0},{"year":"2024","total_paid":12592998.790000003,"total_claims":217589.0,"active_providers":0,"total_beneficiaries":193301.0}],"monthly":null,"top_procedures":[{"code":"99284","description":"Emergency dept visit mod mdm","total_paid":7138519.850000001,"total_claims":41128.0},{"code":"99283","description":"Emergency dept visit low mdm","total_paid":6710648.100000001,"total_claims":38016.0},{"code":"J1745","description":"Infliximab not biosimil 10mg","total_paid":4210020.7299999995,"total_claims":1344.0},{"code":"99285","description":"Emergency dept visit hi mdm","total_paid":3859514.79,"total_claims":23684.0},{"code":"43239","description":"Egd biopsy single/multiple","total_paid":2734450.75,"total_claims":3702.0},{"code":"70450","description":"Ct head/brain w/o dye","total_paid":2629837.8699999996,"total_claims":7868.0},{"code":"90834","description":"Psytx w pt 45 minutes","total_paid":2452842.0099999993,"total_claims":19210.0},{"code":"96415","description":"Chemo iv infusion addl hr","total_paid":2329477.2499999995,"total_claims":3177.0},{"code":"76700","description":"Us exam abdom complete","total_paid":2210525.6999999997,"total_claims":4002.0},{"code":"76856","description":"Us exam pelvic complete","total_paid":2098068.43,"total_claims":3864.0}],"medicare":null}