{"npi":"1407939218","name":"ARK REGIONAL SERVICES, INC","state":"WY","city":"LARAMIE","classification":"Occupational Therapist","total_paid":41615139.56999999,"total_claims":169172.0,"distinct_procedures":11,"avg_per_claim":245.99,"avg_per_claim_zscore":1.43,"classification_avg_per_claim":124.53,"yearly":[{"year":"2018","total_paid":6281836.49,"total_claims":25978.0,"active_providers":0,"total_beneficiaries":2486.0},{"year":"2019","total_paid":6063513.710000001,"total_claims":24324.0,"active_providers":0,"total_beneficiaries":2441.0},{"year":"2020","total_paid":5821420.92,"total_claims":23491.0,"active_providers":0,"total_beneficiaries":2183.0},{"year":"2021","total_paid":5294636.67,"total_claims":22885.0,"active_providers":0,"total_beneficiaries":2192.0},{"year":"2022","total_paid":5837479.16,"total_claims":25045.0,"active_providers":0,"total_beneficiaries":2252.0},{"year":"2023","total_paid":6197416.47,"total_claims":24819.0,"active_providers":0,"total_beneficiaries":2304.0},{"year":"2024","total_paid":6118836.15,"total_claims":22630.0,"active_providers":0,"total_beneficiaries":2109.0}],"monthly":null,"top_procedures":[{"code":"T2016","description":"Habil res waiver per diem","total_paid":24824191.17,"total_claims":108879.0},{"code":"T2021","description":"Day habil waiver per 15 min","total_paid":6944092.06,"total_claims":6730.0},{"code":"T2031","description":"Assist living waiver/diem","total_paid":5644694.58,"total_claims":48174.0},{"code":"T2017","description":"Habil res waiver 15 min","total_paid":1877419.9200000002,"total_claims":2724.0},{"code":"S5100","description":"Adult daycare services 15min","total_paid":1100928.2999999998,"total_claims":982.0},{"code":"S5135","description":"Adult companioncare per 15m","total_paid":969290.73,"total_claims":701.0},{"code":"S5108","description":"Homecare train pt 15 min","total_paid":211732.53,"total_claims":71.0},{"code":"S5130","description":"Homaker service nos per 15m","total_paid":33169.80999999999,"total_claims":474.0},{"code":"99213","description":"Office o/p est low 20 min","total_paid":5686.910000000001,"total_claims":302.0},{"code":"99214","description":"Office o/p est mod 30 min","total_paid":2475.6000000000004,"total_claims":88.0}],"medicare":null}