{"npi":"1528280823","name":"FOREVER YOUNG MEDICAL DAY CARE","state":"NJ","city":"SOMERSET","classification":"Clinic/Center","total_paid":35966423.309999995,"total_claims":447057.0,"distinct_procedures":1,"avg_per_claim":80.45,"avg_per_claim_zscore":-0.33,"classification_avg_per_claim":149.44,"yearly":[{"year":"2018","total_paid":7148602.5,"total_claims":91113.0,"active_providers":0,"total_beneficiaries":4658.0},{"year":"2019","total_paid":5020561.5,"total_claims":64994.0,"active_providers":0,"total_beneficiaries":3271.0},{"year":"2020","total_paid":3547083.0,"total_claims":50574.0,"active_providers":0,"total_beneficiaries":2440.0},{"year":"2021","total_paid":4573785.8,"total_claims":54732.0,"active_providers":0,"total_beneficiaries":2700.0},{"year":"2022","total_paid":4792670.4,"total_claims":56859.0,"active_providers":0,"total_beneficiaries":2710.0},{"year":"2023","total_paid":5401648.5,"total_claims":63175.0,"active_providers":0,"total_beneficiaries":3045.0},{"year":"2024","total_paid":5482071.609999999,"total_claims":65610.0,"active_providers":0,"total_beneficiaries":3240.0}],"monthly":null,"top_procedures":[{"code":"S5102","description":"Adult day care per diem","total_paid":35966423.309999995,"total_claims":447057.0}],"medicare":null}