{"npi":"1689693343","name":"STANLEY STREET TREATMENT AND RESOURCES, INC.","state":"MA","city":"FALL RIVER","classification":"Clinic/Center","total_paid":38397509.41,"total_claims":1176531.0,"distinct_procedures":28,"avg_per_claim":32.64,"avg_per_claim_zscore":-0.56,"classification_avg_per_claim":149.44,"yearly":[{"year":"2018","total_paid":6005326.9,"total_claims":263401.0,"active_providers":0,"total_beneficiaries":29762.0},{"year":"2019","total_paid":5212431.33,"total_claims":235853.0,"active_providers":0,"total_beneficiaries":28193.0},{"year":"2020","total_paid":4121426.6999999993,"total_claims":208068.0,"active_providers":0,"total_beneficiaries":27063.0},{"year":"2021","total_paid":4061394.57,"total_claims":182245.0,"active_providers":0,"total_beneficiaries":27023.0},{"year":"2022","total_paid":5701018.409999999,"total_claims":195967.0,"active_providers":0,"total_beneficiaries":26867.0},{"year":"2023","total_paid":7243030.000000001,"total_claims":50283.0,"active_providers":0,"total_beneficiaries":21943.0},{"year":"2024","total_paid":6052881.5,"total_claims":40714.0,"active_providers":0,"total_beneficiaries":18810.0}],"monthly":null,"top_procedures":[{"code":"H0020","description":"Alcohol and/or drug services","total_paid":12198235.27,"total_claims":951632.0},{"code":"G2067","description":"Med assist tx meth wk","total_paid":7356043.74,"total_claims":58502.0},{"code":"G0470","description":"Fqhc visit, mh estab pt","total_paid":4145624.019999999,"total_claims":23520.0},{"code":"H2015","description":"Comp comm supp svc, 15 min","total_paid":3746947.9499999997,"total_claims":31606.0},{"code":"T1040","description":"Comm bh clinic svc per diem","total_paid":2417820.8,"total_claims":20253.0},{"code":"H2016","description":"Comp comm supp svc, per diem","total_paid":1660483.87,"total_claims":4225.0},{"code":"H0015","description":"Alcohol and/or drug services","total_paid":1488428.61,"total_claims":12191.0},{"code":"H0011","description":"Alcohol and/or drug services","total_paid":1362283.2,"total_claims":868.0},{"code":"90834","description":"Psytx w pt 45 minutes","total_paid":970853.3499999997,"total_claims":12465.0},{"code":"90832","description":"Psytx w pt 30 minutes","total_paid":635935.3699999999,"total_claims":16045.0}],"medicare":{"payment":672752.6,"services":3456.0,"beneficiaries":81.0,"dual_eligible":81.0,"provider_type":"Opioid Treatment Program"}}