{"npi":"1730479254","name":"URGENT CARE MEDICAL ASSOCIATES, LLC","state":"CT","city":"BROOKFIELD","classification":"Clinic/Center","total_paid":39870570.61000001,"total_claims":790944.0,"distinct_procedures":36,"avg_per_claim":50.41,"avg_per_claim_zscore":-0.47,"classification_avg_per_claim":149.44,"yearly":[{"year":"2018","total_paid":2726056.8400000003,"total_claims":55065.0,"active_providers":0,"total_beneficiaries":48866.0},{"year":"2019","total_paid":3117912.450000001,"total_claims":60587.0,"active_providers":0,"total_beneficiaries":55158.0},{"year":"2020","total_paid":4625616.95,"total_claims":94431.0,"active_providers":0,"total_beneficiaries":84974.0},{"year":"2021","total_paid":6775351.790000001,"total_claims":164953.0,"active_providers":0,"total_beneficiaries":148528.0},{"year":"2022","total_paid":6230420.059999999,"total_claims":134273.0,"active_providers":0,"total_beneficiaries":123407.0},{"year":"2023","total_paid":8425180.360000005,"total_claims":149588.0,"active_providers":0,"total_beneficiaries":137589.0},{"year":"2024","total_paid":7970032.160000005,"total_claims":132047.0,"active_providers":0,"total_beneficiaries":120709.0}],"monthly":null,"top_procedures":[{"code":"99214","description":"Office o/p est mod 30 min","total_paid":11474117.83,"total_claims":150744.0},{"code":"99213","description":"Office o/p est low 20 min","total_paid":6792188.749999998,"total_claims":129824.0},{"code":"99203","description":"Office o/p new low 30 min","total_paid":6437870.860000001,"total_claims":82790.0},{"code":"99204","description":"Office o/p new mod 45 min","total_paid":6347807.870000002,"total_claims":55840.0},{"code":"87636","description":"Sarscov2 & inf a&b amp prb","total_paid":2601164.22,"total_claims":24810.0},{"code":"87426","description":"Sarscov coronavirus ag ia","total_paid":1427821.4,"total_claims":50943.0},{"code":"99051","description":"Med serv eve/wkend/holiday","total_paid":831648.0099999993,"total_claims":147315.0},{"code":"87631","description":"Resp virus 3-5 targets","total_paid":742563.6599999997,"total_claims":7653.0},{"code":"99202","description":"Office o/p new sf 15 min","total_paid":727848.0100000001,"total_claims":12912.0},{"code":"87651","description":"Strep a dna amp probe","total_paid":713533.53,"total_claims":26700.0}],"medicare":null}