{"npi":"1962763375","name":"LOVING HANDS HOME HEALTH AGENCY, INC.","state":"FL","city":"FORT MYERS","classification":"Home Health","total_paid":51346166.349999994,"total_claims":54051.0,"distinct_procedures":3,"avg_per_claim":949.96,"avg_per_claim_zscore":3.11,"classification_avg_per_claim":208.1,"yearly":[{"year":"2019","total_paid":3223140.05,"total_claims":3971.0,"active_providers":0,"total_beneficiaries":285.0},{"year":"2020","total_paid":9080027.77,"total_claims":7592.0,"active_providers":0,"total_beneficiaries":349.0},{"year":"2021","total_paid":7168598.910000001,"total_claims":7845.0,"active_providers":0,"total_beneficiaries":336.0},{"year":"2022","total_paid":9510691.31,"total_claims":10133.0,"active_providers":0,"total_beneficiaries":402.0},{"year":"2023","total_paid":12286669.370000001,"total_claims":12750.0,"active_providers":0,"total_beneficiaries":495.0},{"year":"2024","total_paid":10077038.94,"total_claims":11760.0,"active_providers":0,"total_beneficiaries":479.0}],"monthly":null,"top_procedures":[{"code":"S9123","description":"Nursing care in home rn","total_paid":51227340.849999994,"total_claims":51697.0},{"code":"S5130","description":"Homaker service nos per 15m","total_paid":84698.5,"total_claims":1791.0},{"code":"T1004","description":"Nsg aide service up to 15min","total_paid":34127.0,"total_claims":563.0}],"medicare":null}