{"code":"88305","description":"Tissue exam by pathologist","total_paid":1442671301.9400094,"total_claims":33352065.0,"provider_count":10,"yearly":[{"year":"2018","total_paid":158633595.8299997,"total_claims":4222660.0,"active_providers":4888},{"year":"2019","total_paid":184489163.14999998,"total_claims":4643499.0,"active_providers":4898},{"year":"2020","total_paid":175099602.61999962,"total_claims":4077847.0,"active_providers":5026},{"year":"2021","total_paid":229765749.93000007,"total_claims":5253721.0,"active_providers":5303},{"year":"2022","total_paid":232500844.30999994,"total_claims":5285150.0,"active_providers":5186},{"year":"2023","total_paid":254668549.73000005,"total_claims":5557204.0,"active_providers":5187},{"year":"2024","total_paid":207513796.36999986,"total_claims":4311984.0,"active_providers":4632}],"top_states":[{"state":"CA","total_paid":162357495.14999962,"total_claims":4392923.0,"provider_count":830},{"state":"NY","total_paid":161515883.78000006,"total_claims":2525007.0,"provider_count":643},{"state":"NJ","total_paid":72702026.30999997,"total_claims":1287673.0,"provider_count":209},{"state":"OH","total_paid":62740683.83999996,"total_claims":1822648.0,"provider_count":336},{"state":"AZ","total_paid":57978638.4,"total_claims":943612.0,"provider_count":139},{"state":"KY","total_paid":49786570.659999974,"total_claims":878019.0,"provider_count":129},{"state":"NC","total_paid":49698275.33,"total_claims":1017749.0,"provider_count":180},{"state":"FL","total_paid":49587819.47999996,"total_claims":1241329.0,"provider_count":446},{"state":"MA","total_paid":41682390.969999984,"total_claims":1530047.0,"provider_count":352},{"state":"PR","total_paid":40374835.510000005,"total_claims":476153.0,"provider_count":32}],"top_providers":[{"npi":"1740460583","name":"HATO REY PATHOLOGY ASSOCIATES INC","state":"PR","total_paid":11464633.120000005,"total_claims":126283.0},{"npi":"1760480503","name":"PHOENIX CHILDREN'S HOSPITAL","state":"AZ","total_paid":9462568.899999999,"total_claims":13211.0},{"npi":"1598760985","name":"YOSEMITE PATHOLOGY MEDICAL GROUP, INC","state":"CA","total_paid":8964702.26,"total_claims":202373.0},{"npi":"1205835600","name":"P & C LABS, LLC","state":"KY","total_paid":8923498.519999996,"total_claims":93484.0},{"npi":"1174503999","name":"PATHOLOGY SPECIALIST OF ARIZONA, LLP","state":"AZ","total_paid":8486027.239999995,"total_claims":130694.0},{"npi":"1366479099","name":"UNILAB CORPORATION","state":"CA","total_paid":8460968.569999998,"total_claims":340929.0},{"npi":"1871627067","name":"THE DELTA PATHOLOGY GROUP LLC","state":"LA","total_paid":8333088.8999999985,"total_claims":115251.0},{"npi":"1003863580","name":"ASSOCIATED PATHOLOGISTS, LLC","state":"TN","total_paid":7762069.800000005,"total_claims":223882.0},{"npi":"1467433292","name":"INFORM DIAGNOSTICS, INC.","state":"TX","total_paid":7663465.110000001,"total_claims":191891.0},{"npi":"1326086745","name":"INCYTE PATHOLOGY, P.S.","state":"WA","total_paid":6914538.120000002,"total_claims":150797.0}]}