{"code":"DC","name":"District of Columbia","headline":{"total_paid":6106392050.819994,"total_claims":66083942.0,"provider_count":1354,"avg_per_claim":92.40356834070211,"national_rank":39,"national_pct":0.56},"supplementary":{"expanded":true,"expansion_year":2014,"managed_care_pct":96.0,"ffs_pct":4.0,"ffs_caveat":true,"enrollment_trend":[{"year":"2018","enrollment":261274,"ffs_spending":689008301.4000008,"per_enrollee":2637.11,"managed_care_pct":92.8,"ffs_pct":7.2},{"year":"2019","enrollment":261487,"ffs_spending":686977517.6199987,"per_enrollee":2627.2,"managed_care_pct":93.2,"ffs_pct":6.8},{"year":"2020","enrollment":260269,"ffs_spending":693219216.0399991,"per_enrollee":2663.47,"managed_care_pct":93.3,"ffs_pct":6.7},{"year":"2021","enrollment":269339,"ffs_spending":766565029.3499988,"per_enrollee":2846.1,"managed_care_pct":94.0,"ffs_pct":6.0},{"year":"2022","enrollment":295498,"ffs_spending":1098618211.290002,"per_enrollee":3717.85,"managed_care_pct":96.1,"ffs_pct":3.9},{"year":"2023","enrollment":290981,"ffs_spending":1142033243.229999,"per_enrollee":3924.77,"managed_care_pct":95.2,"ffs_pct":4.8},{"year":"2024","enrollment":267104,"ffs_spending":1029970531.8900023,"per_enrollee":3856.07,"managed_care_pct":96.0,"ffs_pct":4.0}]},"yearly":[{"year":"2018","total_paid":689008301.4000008,"total_claims":9330650.0,"active_providers":0},{"year":"2019","total_paid":686977517.6199987,"total_claims":9322827.0,"active_providers":0},{"year":"2020","total_paid":693219216.0399991,"total_claims":8595949.0,"active_providers":0},{"year":"2021","total_paid":766565029.3499988,"total_claims":9213787.0,"active_providers":0},{"year":"2022","total_paid":1098618211.290002,"total_claims":10858752.0,"active_providers":0},{"year":"2023","total_paid":1142033243.229999,"total_claims":10355051.0,"active_providers":0},{"year":"2024","total_paid":1029970531.8900023,"total_claims":8406926.0,"active_providers":0}],"yoy_growth":[{"year":"2018","total_paid":689008301.4,"total_claims":9330650.0,"yoy_paid_growth_pct":null,"yoy_claims_growth_pct":null},{"year":"2019","total_paid":686977517.6200002,"total_claims":9322827.0,"yoy_paid_growth_pct":-0.29,"yoy_claims_growth_pct":-0.08},{"year":"2020","total_paid":693219216.0400001,"total_claims":8595949.0,"yoy_paid_growth_pct":0.91,"yoy_claims_growth_pct":-7.8},{"year":"2021","total_paid":766565029.3499987,"total_claims":9213787.0,"yoy_paid_growth_pct":10.58,"yoy_claims_growth_pct":7.19},{"year":"2022","total_paid":1098618211.2899966,"total_claims":10858752.0,"yoy_paid_growth_pct":43.32,"yoy_claims_growth_pct":17.85},{"year":"2023","total_paid":1142033243.2299955,"total_claims":10355051.0,"yoy_paid_growth_pct":3.95,"yoy_claims_growth_pct":-4.64},{"year":"2024","total_paid":1029970531.8900036,"total_claims":8406926.0,"yoy_paid_growth_pct":-9.81,"yoy_claims_growth_pct":-18.81}],"top_providers":[{"npi":"1396048070","name":"MBI HEALTH SERVICES LLC","state":"DC","city":"WASHINGTON","classification":"Case Management","total_paid":270125586.3100004,"total_claims":2758693.0,"distinct_procedures":57},{"npi":"1912939703","name":"CHILDREN'S HOSPITAL","state":"DC","city":"WASHINGTON","classification":"Clinic/Center","total_paid":242963810.94999987,"total_claims":2196636.0,"distinct_procedures":566},{"npi":"1548378235","name":"MEDSTAR WASHINGTON HOSPITAL CENTER","state":"DC","city":"WASHINGTON","classification":"General Acute Care Hospital","total_paid":239081014.1100001,"total_claims":2832952.0,"distinct_procedures":640},{"npi":"1992805022","name":"GOVERNMENT OF THE DISTRICT OF COLUMBIA OFFICE OF TAX AND REVENUE","state":"DC","city":"WASHINGTON","classification":"Ambulance","total_paid":213401878.96000007,"total_claims":643891.0,"distinct_procedures":4},{"npi":"1407244304","name":"INTEGRATED COMMUNITY SERVICES, INC.","state":"DC","city":"WASHINGTON","classification":"Clinic/Center","total_paid":145741640.14999998,"total_claims":885873.0,"distinct_procedures":6},{"npi":"1487640207","name":"DISTRICT HOSPITAL PARTNERS L P","state":"DC","city":"WASHINGTON","classification":"Nurse Practitioner","total_paid":136253094.59,"total_claims":1835526.0,"distinct_procedures":412},{"npi":"1780800128","name":"CHILDREN'S HOSPITAL","state":"DC","city":"WASHINGTON","classification":"Pediatrics","total_paid":115265710.52999996,"total_claims":1906386.0,"distinct_procedures":292},{"npi":"1184624728","name":"T & N RELIABLE NURSING CARE,LLC","state":"DC","city":"WASHINGTON","classification":"Case Management","total_paid":103292898.47999994,"total_claims":715992.0,"distinct_procedures":5},{"npi":"1700099959","name":"NATIONAL CHILDREN'S CENTER, INC.","state":"DC","city":"WASHINGTON","classification":"Private Vehicle","total_paid":101039801.3,"total_claims":268226.0,"distinct_procedures":9},{"npi":"1780806828","name":"ST. JOHN'S COMMUNITY SERVICES-DC","state":"DC","city":"WASHINGTON","classification":"Community Based Residential Treatment Facility, Intellectual and/or Developmental Disabilities","total_paid":98938037.19000001,"total_claims":271603.0,"distinct_procedures":6},{"npi":"1487740957","name":"HOWARD UNIVERSITY HOSPITAL CORP","state":"DC","city":"WASHINGTON","classification":"General Acute Care Hospital","total_paid":98827737.86000009,"total_claims":1475583.0,"distinct_procedures":378},{"npi":"1700154226","name":"WHC PHYSICIAN GROUP LLC","state":"DC","city":"WASHINGTON","classification":"Dermatology","total_paid":93892528.41999994,"total_claims":1071205.0,"distinct_procedures":129},{"npi":"1619279940","name":"PREVENTIVE MEASURE OF WASHINGTON DC, LLC","state":"DC","city":"WASHINGTON","classification":"Community/Behavioral Health","total_paid":85370809.25000003,"total_claims":994620.0,"distinct_procedures":20},{"npi":"1619400058","name":"SPECIALTY HOME CARE LLC","state":"DC","city":"WASHINGTON","classification":"Home Health","total_paid":85203167.13999997,"total_claims":361369.0,"distinct_procedures":4},{"npi":"1851834501","name":"CAPITAL CARE, INC","state":"DC","city":"WASHINGTON, DC","classification":"Respite Care","total_paid":83583960.72999999,"total_claims":496128.0,"distinct_procedures":3},{"npi":"1376694869","name":"KBC NURSING AGENCY HM HEALTH INC","state":"DC","city":"WASHINGTON","classification":"Community Based Residential Treatment Facility, Intellectual and/or Developmental Disabilities","total_paid":82493171.35,"total_claims":813095.0,"distinct_procedures":5},{"npi":"1598799124","name":"IMMACULATE HEALTH CARE SERVICES,INC","state":"DC","city":"WASHINGTON","classification":"Home Health","total_paid":81891020.53000003,"total_claims":565356.0,"distinct_procedures":6},{"npi":"1114014685","name":"ABA INC","state":"DC","city":"WASHINGTON","classification":"Home Health","total_paid":80816437.13000001,"total_claims":550483.0,"distinct_procedures":2},{"npi":"1366939225","name":"DISTRICT HEALTHCARE SERVICES, LLC","state":"DC","city":"WASHINGTON","classification":"Community/Behavioral Health","total_paid":78109401.32999994,"total_claims":825036.0,"distinct_procedures":22},{"npi":"1841386067","name":"BERHAN HOME HEALTH CARE AGENCY INC","state":"DC","city":"WASHINGTON","classification":"Home Health","total_paid":76856243.3,"total_claims":506286.0,"distinct_procedures":6}],"top_procedures":[{"code":"T1019","description":"Personal care ser per 15 min","total_paid":1378300350.2599998,"total_claims":9848172.0,"provider_count":29,"avg_per_claim":139.9549429335718},{"code":"H0036","description":"Comm psy face-face per 15min","total_paid":796115239.2400002,"total_claims":9083318.0,"provider_count":57,"avg_per_claim":87.64586236439155},{"code":"T2016","description":"Habil res waiver per diem","total_paid":559007288.24,"total_claims":977108.0,"provider_count":17,"avg_per_claim":572.1038905013571},{"code":"T1015","description":"Clinic service","total_paid":187569975.43000016,"total_claims":1720098.0,"provider_count":99,"avg_per_claim":109.0460982048698},{"code":"H0039","description":"Asser com tx face-face/15min","total_paid":155919754.48000014,"total_claims":1420524.0,"provider_count":27,"avg_per_claim":109.7621402243117},{"code":"A0429","description":"Bls-emergency","total_paid":136235766.64,"total_claims":235198.0,"provider_count":3,"avg_per_claim":579.2386271992108},{"code":"99283","description":"Emergency dept visit low mdm","total_paid":124258608.31000002,"total_claims":815157.0,"provider_count":39,"avg_per_claim":152.43518525879065},{"code":"99284","description":"Emergency dept visit mod mdm","total_paid":117297085.38999999,"total_claims":830457.0,"provider_count":34,"avg_per_claim":141.24402032856605},{"code":"99213","description":"Office o/p est low 20 min","total_paid":99025655.61000013,"total_claims":1987356.0,"provider_count":318,"avg_per_claim":49.82783940572305},{"code":"99214","description":"Office o/p est mod 30 min","total_paid":98901163.4899999,"total_claims":1319739.0,"provider_count":311,"avg_per_claim":74.93994152631687},{"code":"99285","description":"Emergency dept visit hi mdm","total_paid":91847089.02000001,"total_claims":637526.0,"provider_count":26,"avg_per_claim":144.06798941533367},{"code":"99212","description":"Office o/p est sf 10 min","total_paid":76447475.41000007,"total_claims":529102.0,"provider_count":131,"avg_per_claim":144.48532685569148},{"code":"H0044","description":"Supported housing, per month","total_paid":75695777.19,"total_claims":282896.0,"provider_count":24,"avg_per_claim":267.57457578049883},{"code":"H0025","description":"Alcohol and/or drug preventi","total_paid":69934214.04,"total_claims":717125.0,"provider_count":25,"avg_per_claim":97.52025663587241},{"code":"A0427","description":"Als1-emergency","total_paid":67220073.56999998,"total_claims":103558.0,"provider_count":4,"avg_per_claim":649.1055598794876},{"code":"T2033","description":"Res, nos waiver per diem","total_paid":63568770.19000002,"total_claims":124739.0,"provider_count":5,"avg_per_claim":509.61423604486185},{"code":"T2021","description":"Day habil waiver per 15 min","total_paid":62928348.870000005,"total_claims":416296.0,"provider_count":28,"avg_per_claim":151.16251145819322},{"code":"99509","description":"Home visit day life activity","total_paid":58657123.26000001,"total_claims":416626.0,"provider_count":16,"avg_per_claim":140.79083700969218},{"code":"S5135","description":"Adult companioncare per 15m","total_paid":56545928.06999999,"total_claims":323061.0,"provider_count":23,"avg_per_claim":175.0317372570505},{"code":"H0034","description":"Med trng & support per 15min","total_paid":53195108.269999966,"total_claims":561925.0,"provider_count":52,"avg_per_claim":94.66585090536988}],"classification":[{"classification":"Clinic/Center","total_paid":972268705.0399997,"total_claims":14425316.0,"provider_count":164},{"classification":"Home Health","total_paid":670397666.9899999,"total_claims":4571037.0,"provider_count":24},{"classification":"Case Management","total_paid":585302589.7499993,"total_claims":5908307.0,"provider_count":45},{"classification":"Community/Behavioral Health","total_paid":453972798.7100003,"total_claims":4814497.0,"provider_count":35},{"classification":"General Acute Care Hospital","total_paid":419169838.4000007,"total_claims":5560411.0,"provider_count":4},{"classification":"Community Based Residential Treatment Facility, Intellectual and/or Developmental Disabilities","total_paid":344027590.0,"total_claims":1491619.0,"provider_count":14},{"classification":"Respite Care","total_paid":287529796.88,"total_claims":2098140.0,"provider_count":5},{"classification":"Ambulance","total_paid":220010129.09000003,"total_claims":715269.0,"provider_count":3},{"classification":"Counselor","total_paid":211636026.89000008,"total_claims":2104089.0,"provider_count":37},{"classification":"Dermatology","total_paid":169741403.56,"total_claims":2559898.0,"provider_count":6},{"classification":"Nurse Practitioner","total_paid":149621888.98999998,"total_claims":2089096.0,"provider_count":50},{"classification":"Pediatrics","total_paid":146769511.6,"total_claims":2662246.0,"provider_count":41},{"classification":"Dentist","total_paid":146239424.51000008,"total_claims":2758218.0,"provider_count":219},{"classification":"Assisted Living Facility","total_paid":137163811.34000003,"total_claims":360025.0,"provider_count":7},{"classification":"Durable Medical Equipment & Medical Supplies","total_paid":136896514.25999993,"total_claims":1300191.0,"provider_count":34},{"classification":"Day Training, Developmentally Disabled Services","total_paid":107424598.25,"total_claims":620456.0,"provider_count":16},{"classification":"Internal Medicine","total_paid":101804802.28999995,"total_claims":2269325.0,"provider_count":133},{"classification":"Private Vehicle","total_paid":101039801.3,"total_claims":268226.0,"provider_count":1},{"classification":"Intermediate Care Facility, Intellectual Disabilities","total_paid":83723428.74000001,"total_claims":145385.0,"provider_count":3},{"classification":"In Home Supportive Care","total_paid":72854276.36000001,"total_claims":448038.0,"provider_count":4}],"concentration":[{"provider_tier":"Top 1%","provider_count":13,"tier_total_paid":1944194548.0999992,"pct_of_total":31.84},{"provider_tier":"Top 5%","provider_count":54,"tier_total_paid":2694345238.57,"pct_of_total":44.12},{"provider_tier":"Top 10%","provider_count":68,"tier_total_paid":841605049.4299998,"pct_of_total":13.78},{"provider_tier":"Top 20%","provider_count":135,"tier_total_paid":436825999.9499997,"pct_of_total":7.15},{"provider_tier":"Bottom 80%","provider_count":1084,"tier_total_paid":189421214.77000016,"pct_of_total":3.1}]}